django_fancy_cronfield-0.2.0.dist-info/DESCRIPTION.rst
django_fancy_cronfield-0.2.0.dist-info/METADATA
django_fancy_cronfield-0.2.0.dist-info/RECORD
django_fancy_cronfield-0.2.0.dist-info/WHEEL
django_fancy_cronfield-0.2.0.dist-info/metadata.json
django_fancy_cronfield-0.2.0.dist-info/top_level.txt
fancy_cronfield/__init__.py
fancy_cronfield/fields.py
fancy_cronfield/models.py
fancy_cronfield/validators.py
fancy_cronfield/widgets.py
fancy_cronfield/locale/fa/LC_MESSAGES/django.mo
fancy_cronfield/locale/fa/LC_MESSAGES/django.po
fancy_cronfield/locale/fa/LC_MESSAGES/djangojs.mo
fancy_cronfield/locale/fa/LC_MESSAGES/djangojs.po
fancy_cronfield/locale/fr/LC_MESSAGES/django.mo
fancy_cronfield/locale/fr/LC_MESSAGES/django.po
fancy_cronfield/locale/fr/LC_MESSAGES/djangojs.mo
fancy_cronfield/locale/fr/LC_MESSAGES/djangojs.po
fancy_cronfield/static/fancy_cronfield/css/cronfield.css
fancy_cronfield/static/fancy_cronfield/css/cronfield.min.css
fancy_cronfield/static/fancy_cronfield/css/jquery-cron.css
fancy_cronfield/static/fancy_cronfield/css/jquery-cron.min.css
fancy_cronfield/static/fancy_cronfield/css/jquery-gentleSelect.css
fancy_cronfield/static/fancy_cronfield/css/jquery-gentleSelect.min.css
fancy_cronfield/static/fancy_cronfield/img/disk.png
fancy_cronfield/static/fancy_cronfield/img/expand.png
fancy_cronfield/static/fancy_cronfield/img/loading.gif
fancy_cronfield/static/fancy_cronfield/js/cronfield.js
fancy_cronfield/static/fancy_cronfield/js/cronfield.min.js
fancy_cronfield/static/fancy_cronfield/js/jquery-1.4.1.min.js
fancy_cronfield/static/fancy_cronfield/js/jquery-cron.js
fancy_cronfield/static/fancy_cronfield/js/jquery-cron.min.js
fancy_cronfield/static/fancy_cronfield/js/jquery-gentleSelect.js
fancy_cronfield/static/fancy_cronfield/js/jquery-gentleSelect.min.js
fancy_cronfield/tests/__init__.py
fancy_cronfield/tests/settings.py
fancy_cronfield/tests/test_fields.py
fancy_cronfield/tests/test_validators.py
fancy_cronfield/tests/test_widgets.py
fancy_cronfield/utils/__init__.py
fancy_cronfield/utils/compat/__init__.py
